ffmpeg/__init__.py
ffmpeg/audio.py
ffmpeg/image.py
ffmpeg/stream.py
ffmpeg/video.py
ffmpeg_wheel-1.4.dist-info/METADATA
ffmpeg_wheel-1.4.dist-info/WHEEL
ffmpeg_wheel-1.4.dist-info/top_level.txt
ffmpeg_wheel-1.4.dist-info/RECORD
