Metadata-Version: 2.1
Name: ffmpeg-wheel
Version: 1.4
Summary: ffmpeg python package url [https://github.com/jiashaokun/ffmpeg]
Home-page: https://github.com/jiashaokun/ffmpeg
Author: SkeyJIA
Author-email: 363604236@qq.com
License: MIT Licence
Keywords: python ffmpeg
Platform: any
